README.md
setup.py
conspiracy/__init__.py
conspiracy/example.py
conspiracy/log.py
conspiracy/plot.py
conspiracy.egg-info/PKG-INFO
conspiracy.egg-info/SOURCES.txt
conspiracy.egg-info/dependency_links.txt
conspiracy.egg-info/requires.txt
conspiracy.egg-info/top_level.txt