Metadata-Version: 2.1
Name: conspiracy
Version: 0.0.1
Summary: Terminal Plotter
Home-page: https://github.com/aaronwalsman/conspiracy
Author: Aaron Walsman
Author-email: aaronwalsman@gmail.com
License: MIT
